{
  "Electronics": {
    "Smartphone": 93.47,
    "Laptop": 1194.05,
    "Tablet": 1370.2,
    "Desktop PC": 1527.65,
    "Smartwatch": 1287.95,
    "Television": 357.67,
    "Gaming Console": 271.36,
    "Camera": 363.58,
    "Printer": 517.3,
    "Monitor": 768.83,
    "Keyboard": 1690.15,
    "Mouse": 936.55,
    "Headphones": 1668.09,
    "Bluetooth Speaker": 1520.23,
    "Router": 484.05,
    "Smart Home Hub": 808.53,
    "Drone": 371.97,
    "E-reader": 1609.35,
    "Fitness Tracker": 299.19,
    "VR Headset": 1808.4,
    "Portable Charger": 474.15,
    "External Hard Drive": 1760.29,
    "Smart Light Bulb": 699.51,
    "Smart Thermostat": 766.55,
    "Electric Toothbrush": 1020.1,
    "Electric Shaver": 511.88,
    "Microwave": 1301.15,
    "Blender": 1682.7,
    "Coffee Maker": 390.86,
    "Refrigerator": 148.33,
    "Projector": 276.2,
    "Action Camera": 1543.68,
    "Wireless Earbuds": 1651.39,
    "Gaming Mouse": 935.1,
    "Graphics Tablet": 1146.57,
    "External SSD": 644.41,
    "Smart Scale": 644.9,
    "Robot Vacuum": 906.67,
    "Electric Scooter": 1983.06,
    "Digital Camera": 1849.48,
    "Smart Lock": 1274.82,
    "Portable Projector": 452.84,
    "Mini PC": 1156.68,
    "Desk Lamp": 870.82,
    "Voice Assistant": 745.65,
    "Fitness Band": 1161.31,
    "Smart Mirror": 1888.46,
    "Smart Doorbell": 234.56,
    "Smart Plug": 89.99,
    "Portable Power Station": 456.78,
    "Streaming Device": 123.45,
    "Smart Display": 678.90,
    "Smart Glasses": 1234.56,
    "Smart Pen": 45.67,
    "Smart Speaker": 234.89,
    "Smart Refrigerator": 2000.0,
    "Electric Kettle": 50.0,
    "Smart Oven": 1500.0,
    "Wireless Charger": 40.0,
    "Digital Photo Frame": 60.0,
    "Smart Smoke Detector": 80.0,
    "Smart Security Camera": 120.0,
    "Electric Car": 35000.0,
    "3D Printer": 700.0,
    "Electric Bike": 1200.0,
    "Smart Bed": 2500.0
  },
  "Clothing": {
    "T-shirt": 57.77,
    "Jeans": 47.44,
    "Jacket": 69.68,
    "Sweater": 171.72,
    "Hoodie": 46.55,
    "Blazer": 186.68,
    "Dress": 155.22,
    "Skirt": 136.76,
    "Shorts": 53.53,
    "Pants": 118.79,
    "Suit": 93.19,
    "Coat": 157.44,
    "Scarf": 19.91,
    "Hat": 171.86,
    "Gloves": 172.95,
    "Socks": 59.94,
    "Shoes": 128.72,
    "Sandals": 163.96,
    "Boots": 179.41,
    "Sneakers": 129.97,
    "Belt": 83.06,
    "Tie": 123.45,
    "Blouse": 162.67,
    "Cardigan": 136.2,
    "Vest": 77.47,
    "Polo Shirt": 45.42,
    "Tank Top": 131.55,
    "Leggings": 115.95,
    "Overalls": 194.29,
    "Swimsuit": 155.07,
    "Sweatshirt": 69.28,
    "Parka": 50.84,
    "Jumpsuit": 85.5,
    "Kimono": 141.29,
    "Tuxedo": 11.58,
    "Peacoat": 57.99,
    "Anorak": 85.86,
    "Windbreaker": 133.63,
    "Chinos": 188.79,
    "Raincoat": 199.07,
    "Poncho": 160.62,
    "Fleece": 167.8,
    "Culottes": 158.34,
    "Bomber Jacket": 13.76,
    "Fedora": 143.21,
    "Beanie": 26.63,
    "Flip-flops": 188.61,
    "Espadrilles": 45.57,
    "Loafers": 153.25,
    "Slippers": 77.3,
    "Wetsuit": 83.82,
    "Bow Tie": 67.71,
    "Waistcoat": 176.28,
    "Sarong": 104.01,
    "Harem Pants": 112.79,
    "Turtleneck": 193.0,
    "Pajamas": 188.27,
    "Swim Trunks": 49.16,
    "Apron": 90.74,
    "Uniform": 58.2,
    "Sunglasses": 23.45,
    "Ballet Shoes": 34.56,
    "Running Shoes": 45.67,
    "Yoga Pants": 56.78,
    "Winter Hat": 67.89,
    "Rain Boots": 78.90,
    "High Heels": 89.01,
    "Bowler Hat": 90.12,
    "Suspenders": 101.23,
    "Mittens": 112.34,
    "Tracksuit": 80.0,
    "Bathrobe": 40.0,
    "Nightgown": 50.0,
    "Coveralls": 60.0,
    "Tankini": 70.0,
    "Bodysuit": 30.0,
    "Romper": 50.0,
    "Capris": 40.0,
    "Cargo Pants": 60.0,
    "Camisole": 20.0,
    "Kaftan": 100.0,
    "Shrug": 35.0,
    "Board Shorts": 45.0
  },
  "Food": {
    "Apple": 14.85,
    "Banana": 8.95,
    "Orange": 13.6,
    "Grapes": 4.64,
    "Strawberry": 11.74,
    "Blueberry": 16.47,
    "Mango": 11.57,
    "Pineapple": 11.61,
    "Watermelon": 1.49,
    "Kiwi": 19.77,
    "Tomato": 19.81,
    "Cucumber": 7.42,
    "Carrot": 6.42,
    "Broccoli": 3.93,
    "Spinach": 18.19,
    "Potato": 19.87,
    "Pumpkin": 16.11,
    "Peas": 10.05,
    "Bell Pepper": 5.59,
    "Onion": 1.46,
    "Garlic": 7.6,
    "Ginger": 9.34,
    "Lettuce": 13.42,
    "Cabbage": 15.93,
    "Cauliflower": 4.3,
    "Mushroom": 6.88,
    "Zucchini": 2.1,
    "Eggplant": 19.68,
    "Corn": 12.96,
    "Papaya": 3.74,
    "Avocado": 18.04,
    "Peach": 16.77,
    "Pear": 19.42,
    "Plum": 19.71,
    "Cherry": 6.95,
    "Apricot": 13.23,
    "Fig": 6.16,
    "Date": 1.8,
    "Raspberry": 8.01,
    "Blackberry": 4.76,
    "Coconut": 4.53,
    "Pomegranate": 19.45,
    "Celery": 8.81,
    "Radish": 3.88,
    "Beetroot": 2.78,
    "Brussels Sprouts": 3.45,
    "Turnip": 4.56,
    "Parsnip": 5.67,
    "Kale": 6.78,
    "Leek": 7.89,
    "Artichoke": 8.90,
    "Asparagus": 9.01,
    "Bok Choy": 10.12,
    "Butternut Squash": 11.23,
    "Chard": 12.34,
    "Endive": 13.45,
    "Fennel": 14.56,
    "Lemon": 0.50,
    "Lime": 0.40,
    "Grapefruit": 1.00,
    "Mandarin": 0.60,
    "Tangerine": 0.70,
    "Melon": 3.00,
    "Passion Fruit": 1.50,
    "Lychee": 2.00,
    "Dragon Fruit": 5.00,
    "Starfruit": 4.00,
    "Guava": 1.80,
    "Durian": 15.00,
    "Sugar Apple": 2.50,
    "Jackfruit": 12.00

  }
}